[
  {
    "id": 1,
    "number": "01",
    "slug": "crafted",
    "title": "Crafted",
    "client": "Saanjh Apparel",
    "category": "Brand Film",
    "year": "2024",
    "description": "A 60-second cinematic brand film for a homegrown apparel label — shot over two days and built to make a regional brand feel national. From mood-board to final grade, every frame was designed to sell a feeling, not just a product.",
    "deliverables": ["Concept & Script", "Direction", "2-Day Shoot", "Color Grade", "Sound Design"],
    "video": "/videos/film-project.mp4",
    "image": "https://images.unsplash.com/photo-1485846234645-a62644f84728?auto=format&fit=crop&w=1200&q=80",
    "clips": [
      { "title": "Final Film", "src": "/videos/film-project.mp4" },
      { "title": "30s Cut", "src": "/videos/brand.mp4" },
      { "title": "Behind the Scenes", "src": "/videos/v3.mp4" },
      { "title": "Teaser", "src": "/videos/cars-hero.mp4" },
      { "title": "Product Insert", "src": "/videos/v1.mp4" },
      { "title": "Social Cutdown", "src": "/videos/vines.mp4" },
      { "title": "Director's Cut", "src": "/videos/cars-hero.mp4" },
      { "title": "Color Test", "src": "/videos/cars-hero-alt.mp4" },
      { "title": "Vertical Cut", "src": "/videos/v4.mp4" }
    ]
  },
  {
    "id": 2,
    "number": "02",
    "slug": "echoes",
    "title": "Echoes",
    "client": "Raghav — Independent Artist",
    "category": "Music Video",
    "year": "2024",
    "description": "A performance-meets-narrative music video for an independent artist's debut single. Moody lighting, handheld energy and rhythm-locked cuts turned a small budget into a video that crossed a million plays.",
    "deliverables": ["Treatment", "Cinematography", "Performance Shoot", "Edit", "VFX Cleanup"],
    "video": "/videos/music-project.mp4",
    "image": "https://images.unsplash.com/photo-1511671782779-c97d3d27a1d4?auto=format&fit=crop&w=1200&q=80",
    "clips": [
      { "title": "Music Video", "src": "/videos/music-project.mp4" },
      { "title": "Performance Take", "src": "/videos/song.mp4" },
      { "title": "Behind the Scenes", "src": "/videos/visual-project.mp4" },
      { "title": "Lyric Cut", "src": "/videos/v4.mp4" },
      { "title": "Teaser", "src": "/videos/hero.mp4" },
      { "title": "Reel", "src": "/videos/vines.mp4" },
      { "title": "Acoustic Version", "src": "/videos/v3.mp4" },
      { "title": "Studio Session", "src": "/videos/v1.mp4" },
      { "title": "Vertical Cut", "src": "/videos/comedy.mp4" }
    ]
  },
  {
    "id": 3,
    "number": "03",
    "slug": "punchline",
    "title": "Punchline",
    "client": "Creator Collab",
    "category": "Comedy Series",
    "year": "2023",
    "description": "A scripted comedy series for a YouTube creator — tight writing, fast timing and edits engineered for retention. Episode one became the channel's most-watched upload to date.",
    "deliverables": ["Scripting", "Production", "Comedy Edit", "Thumbnail Design"],
    "video": "/videos/comedy-project.mp4",
    "image": "https://images.unsplash.com/photo-1543007630-9710e4a00a20?auto=format&fit=crop&w=1200&q=80",
    "clips": [
      { "title": "Episode 1", "src": "/videos/comedy-project.mp4" },
      { "title": "Sketch", "src": "/videos/comedy.mp4" },
      { "title": "Cold Open", "src": "/videos/v3.mp4" },
      { "title": "Bloopers", "src": "/videos/v1.mp4" },
      { "title": "Promo", "src": "/videos/vines.mp4" },
      { "title": "Trailer", "src": "/videos/hero-alt.mp4" },
      { "title": "Outtakes", "src": "/videos/v4.mp4" },
      { "title": "Live Set", "src": "/videos/visual-project.mp4" },
      { "title": "Short", "src": "/videos/cars-hero.mp4" }
    ]
  },
  {
    "id": 4,
    "number": "04",
    "slug": "scroll-stoppers",
    "title": "Scroll Stoppers",
    "client": "D2C Skincare Brand",
    "category": "Reels & Shorts",
    "year": "2024",
    "description": "A month-long short-form campaign — twelve reels built to stop the scroll in the first second. Hook-first editing and trend-aware sound design tripled the brand's average reach in four weeks.",
    "deliverables": ["Content Strategy", "Shoot", "12 Reels", "Captions & Motion"],
    "video": "/videos/vines.mp4",
    "image": "https://images.unsplash.com/photo-1574717024653-61fd2cf4d44d?auto=format&fit=crop&w=1200&q=80",
    "clips": [
      { "title": "Reel 01", "src": "/videos/vines.mp4" },
      { "title": "Reel 02", "src": "/videos/v4.mp4" },
      { "title": "Reel 03", "src": "/videos/v1.mp4" },
      { "title": "Hook Test", "src": "/videos/comedy.mp4" },
      { "title": "Product Reel", "src": "/videos/brand.mp4" },
      { "title": "Trend Cut", "src": "/videos/song.mp4" },
      { "title": "Reel 04", "src": "/videos/v3.mp4" },
      { "title": "Reel 05", "src": "/videos/visual-project.mp4" },
      { "title": "Reel 06", "src": "/videos/hero.mp4" }
    ]
  },
  {
    "id": 5,
    "number": "05",
    "slug": "reframe",
    "title": "Reframe",
    "client": "Early-stage Startup",
    "category": "Design + Motion",
    "year": "2023",
    "description": "A full brand identity and animated launch reveal for a tech startup — logo system, type, colour and a motion reveal that gave the launch a premium, well-funded feel from day one.",
    "deliverables": ["Brand Identity", "Logo Animation", "Launch Promo", "Social Kit"],
    "video": "/videos/animation-project.mp4",
    "image": "https://images.unsplash.com/photo-1626785774573-4b799315345d?auto=format&fit=crop&w=1200&q=80",
    "clips": [
      { "title": "Logo Reveal", "src": "/videos/animation-project.mp4" },
      { "title": "Motion Sample (YouTube)", "src": "https://youtu.be/aqz-KE-bpKQ" },
      { "title": "Brand Loop", "src": "/videos/visual-project.mp4" },
      { "title": "Title Sequence", "src": "/videos/cars-hero.mp4" },
      { "title": "Social Kit", "src": "/videos/vines.mp4" },
      { "title": "Promo", "src": "/videos/v1.mp4" },
      { "title": "Lower Thirds", "src": "/videos/v4.mp4" },
      { "title": "Transition Pack", "src": "/videos/v3.mp4" },
      { "title": "Outro", "src": "/videos/animation-project.mp4" }
    ]
  },
  {
    "id": 6,
    "number": "06",
    "slug": "the-makers",
    "title": "The Makers",
    "client": "FPS Originals",
    "category": "Documentary",
    "year": "2024",
    "description": "An in-house documentary short following local craftspeople — a slower, story-first piece that proves the studio can hold a quiet, human narrative just as well as a high-energy ad.",
    "deliverables": ["Research", "Interviews", "Cinematography", "Long-form Edit"],
    "video": "/videos/doc-project.mp4",
    "image": "https://images.unsplash.com/photo-1492691527719-9d1e07e534b4?auto=format&fit=crop&w=1200&q=80",
    "clips": [
      { "title": "Documentary", "src": "/videos/doc-project.mp4" },
      { "title": "Interview", "src": "/videos/v3.mp4" },
      { "title": "B-Roll", "src": "/videos/visual-project.mp4" },
      { "title": "Trailer", "src": "/videos/hero.mp4" },
      { "title": "Portrait", "src": "/videos/v4.mp4" },
      { "title": "Field Notes", "src": "/videos/song.mp4" },
      { "title": "Chapter 2", "src": "/videos/v1.mp4" },
      { "title": "Location Scout", "src": "/videos/cars-hero.mp4" },
      { "title": "Epilogue", "src": "/videos/hero-alt.mp4" }
    ]
  }
]
